mcp_screen_operation-0.1.3.dist-info/licenses/LICENSE
screen_operation_server/__init__.py
screen_operation_server/automation.py
screen_operation_server/main.py
screen_operation_server/operations.py
screen_operation_server/window_manager.py
mcp_screen_operation-0.1.3.dist-info/METADATA
mcp_screen_operation-0.1.3.dist-info/WHEEL
mcp_screen_operation-0.1.3.dist-info/entry_points.txt
mcp_screen_operation-0.1.3.dist-info/top_level.txt
mcp_screen_operation-0.1.3.dist-info/RECORD
