Metadata-Version: 2.4
Name: mcp-screen-operation
Version: 0.1.3
Summary: MCP server for screen and window operations.
Author: kakehashi
License: MIT License
Project-URL: Homepage, https://github.com/kakehashi/mcp-screen-operation
Project-URL: Bug Tracker, https://github.com/kakehashi/mcp-screen-operation/issues
Project-URL: Documentation, https://github.com/kakehashi/mcp-screen-operation#readme
Keywords: mcp,automation,screen-capture,window-management,cross-platform
Classifier: Development Status :: 4 - Beta
Classifier: Intended Audience :: Developers
Classifier: License :: OSI Approved :: MIT License
Classifier: Operating System :: OS Independent
Classifier: Programming Language :: Python :: 3
Classifier: Programming Language :: Python :: 3.10
Classifier: Programming Language :: Python :: 3.11
Classifier: Programming Language :: Python :: 3.12
Classifier: Topic :: Software Development :: Libraries :: Python Modules
Requires-Python: >=3.10
License-File: LICENSE
Requires-Dist: mcp>=1.9.4
Requires-Dist: fastmcp>=2.3.0
Requires-Dist: mss
Requires-Dist: Pillow
Requires-Dist: pyautogui
Requires-Dist: pywin32; sys_platform == "win32"
Requires-Dist: python-xlib; sys_platform == "linux"
Requires-Dist: pyobjc-framework-Quartz; sys_platform == "darwin"
Requires-Dist: pyobjc-framework-Cocoa; sys_platform == "darwin"
Provides-Extra: dev
Requires-Dist: pylint; extra == "dev"
Requires-Dist: pylint-plugin-utils; extra == "dev"
Requires-Dist: pylint-mcp; extra == "dev"
Requires-Dist: black; extra == "dev"
Provides-Extra: build
Requires-Dist: build>=1.0.0; extra == "build"
Requires-Dist: twine>=5.0.0; extra == "build"
Requires-Dist: wheel>=0.42.0; extra == "build"
Dynamic: license-file
